nomi/__init__.py
nomi/core/__init__.py
nomi/core/model.py
nomi/core/render.py
nomi/domain/__init__.py
nomi/domain/models/__init__.py
nomi/domain/models/attachment.py
nomi/domain/models/note.py
nomi/domain/models/style.py
nomi/infra/__init__.py
nomi/infra/fetchers/__init__.py
nomi/infra/fetchers/apple.py
nomi/infra/fetchers/base.py
nomi/infra/helper/__init__.py
nomi/infra/helper/apple.py
nomi/infra/renderers/__init__.py
nomi/infra/renderers/base.py
nomi/infra/renderers/markdown.py
nomi/protobuf/__init__.py
nomi/protobuf/notestore_pb2.py
nomi/protobuf/notestore_pb2.pyi
nomi_ai-0.1.0.dist-info/METADATA
nomi_ai-0.1.0.dist-info/WHEEL
nomi_ai-0.1.0.dist-info/RECORD
