Metadata-Version: 2.1
Name: nomi-ai
Version: 0.1.0
Summary: Default template for PDM package
Author-Email: AFuture <afuture.d@outlook.com>
License: MIT
Requires-Python: >=3.12
Requires-Dist: protobuf>=5.26.1
Requires-Dist: sqlalchemy[asyncio]>=2.0.30
Requires-Dist: psycopg[binary]>=3.1.19
